HISTORY.rst
LICENSE.rst
MANIFEST.in
README.rst
setup.py
src/yafowil/__init__.py
src/yafowil.zope2.egg-info/PKG-INFO
src/yafowil.zope2.egg-info/SOURCES.txt
src/yafowil.zope2.egg-info/dependency_links.txt
src/yafowil.zope2.egg-info/entry_points.txt
src/yafowil.zope2.egg-info/namespace_packages.txt
src/yafowil.zope2.egg-info/requires.txt
src/yafowil.zope2.egg-info/top_level.txt
src/yafowil.zope2.egg-info/zip-safe
src/yafowil/zope2/__init__.py
src/yafowil/zope2/configure.zcml
src/yafowil/zope2/connectors.py
src/yafowil/zope2/example.pt
src/yafowil/zope2/example.py
src/yafowil/zope2/meta.py
src/yafowil/zope2/meta.zcml
src/yafowil/zope2/setuphandlers.py
src/yafowil/zope2/profiles/default/metadata.xml
src/yafowil/zope2/profiles/default/yafowil.zope2.txt