Metadata-Version: 1.0
Name: yafowil.zope2
Version: 1.0
Summary: Zope2/ Plone Integration with YAFOWIL
Home-page: http://packages.python.org/yafowil.zope2
Author: BlueDynamics Alliance
Author-email: dev@bluedynamics.com
License: Simplified BSD
Keywords: zope2 request response html input widgets
Platform: UNKNOWN
Classifier: Development Status :: 5 - Production/Stable
Classifier: Operating System :: OS Independent
Classifier: Programming Language :: Python
Classifier: Topic :: Software Development
Classifier: Topic :: Internet :: WWW/HTTP :: Dynamic Content
Classifier: Framework :: Zope2
Classifier: Framework :: Plone
Classifier: License :: OSI Approved :: BSD License
